MyMalDependency_package
