Metadata-Version: 1.0
Name: MyMalDependency
Version: 4.1.1
Summary: test to create package
Home-page: UNKNOWN
Author: 1
Author-email: UNKNOWN
License: UNKNOWN
Platform: UNKNOWN
